mcp_pack/__init__.py
mcp_pack/__main__.py
mcp_pack/clean_db.py
mcp_pack/cli.py
mcp_pack/create_db.py
mcp_pack/db_utils.py
mcp_pack/list_db.py
mcp_pack/server.py
mcp_pack/version.py
mcp_pack-0.3.0.dist-info/METADATA
mcp_pack-0.3.0.dist-info/WHEEL
mcp_pack-0.3.0.dist-info/entry_points.txt
mcp_pack-0.3.0.dist-info/licenses/LICENSE
mcp_pack-0.3.0.dist-info/RECORD
