Metadata-Version: 2.4
Name: mcp-pack
Version: 0.3.0
Summary: Package for accessing package artifacts via MCP
Author: Katherine Rosenfeld
License-File: LICENSE
Requires-Python: >=3.11
Requires-Dist: ipykernel>=6.29.5
Requires-Dist: mcp[cli]>=1.6.0
Requires-Dist: nbconvert>=7.16.6
Requires-Dist: nbformat>=5.10.4
Requires-Dist: openai>=1.75.0
Requires-Dist: python-dotenv>=1.1.0
Requires-Dist: qdrant-client>=1.13.3
Requires-Dist: sentence-transformers>=4.1.0
